EL-3307_template/src/design/binario_7seg.sv
module binario_7seg (
    //Entradas y salidas del modulo
    input  wire [3:0] codigo_bin_pi, // Entrada de los 4 datos
    output wire [6:0] catodo_po // Salida de los 7 bits para el 7 segmentos

);
    // Conexión con las entradas dentro de la FPGA
    wire i3;
    wire i2;
    wire i1;
    wire i0;
    
    // Conexión con las salidas dentro de la FPGA
    wire a;
    wire b;
    wire c;
    wire d;
    wire e;
    wire f;
    wire g;
    
    // Asigna el valor que tenga la entrada de los datos a i3, i2, i1, i0
    assign i3 = codigo_bin_pi[3];
    assign i2 = codigo_bin_pi[2];
    assign i1 = codigo_bin_pi[1];
    assign i0 = codigo_bin_pi[0];

    // Segmento A
    // 0 = encendido, 1 = apagado
    assign a =
          (i0 & i1 & i3 & ~i2) |
          (i0 & i2 & i3 & ~i1) |
          (i0 & ~i1 & ~i2 & ~i3) |
          (i2 & ~i0 & ~i1 & ~i3);

    // Segmento B
    assign b =
          (i0 & i1 & i3) |
          (i1 & i2 & ~i0) |
          (i2 & i3 & ~i0) |
          (i0 & i2 & ~i1 & ~i3);

    // Segmento C
    assign c =
          (i1 & i2 & i3) |
          (i2 & i3 & ~i0) |
          (i1 & ~i0 & ~i2 & ~i3);

    // Segmento D
    assign d =
          (i0 & i1 & i2) |
          (i1 & i3 & ~i0 & ~i2) |
          (i0 & ~i1 & ~i2 & ~i3) |
          (i2 & ~i0 & ~i1 & ~i3);

    // Segmento E
    assign e =
          (i0 & ~i3) |
          (i0 & ~i1 & ~i2) |
          (i2 & ~i1 & ~i3);

    // Segmento F
    assign f =
          (i0 & i1 & ~i3) |
          (i0 & ~i2 & ~i3) |
          (i1 & ~i2 & ~i3) |
          (i0 & i2 & i3 & ~i1);

    // Segmento G
    assign g =
          (i0 & i1 & i2 & ~i3) |
          (~i1 & ~i2 & ~i3) |
          (i2 & i3 & ~i0 & ~i1);


    // ========================================================
    // ORDEN DE PIN CON SEGMENTO
    //
    // FPGA 76 -> A
    // FPGA 75 -> B
    // FPGA 74 -> F
    // FPGA 73 -> C
    // FPGA 72 -> E
    // FPGA 71 -> D
    // FPGA 70 -> G
    // ========================================================

    // Enciende o apaga el catodo del 7 segmentos
    assign catodo_po[0] = a;
    assign catodo_po[1] = b;
    assign catodo_po[2] = e;
    assign catodo_po[3] = d;
    assign catodo_po[4] = g;
    assign catodo_po[5] = f;
    assign catodo_po[6] = c;

endmodule

EL-3307_template/src/sim/tb_binario_7seg.sv
`timescale 1ns/1ps

module binario_7seg_tb;

    // Entradas del DUT
    reg [3:0] codigo_bin_pi;

    // Salidas del DUT
    wire [6:0] catodo_po;

    // Instancia del módulo bajo prueba
    binario_7seg DUT (
        .codigo_bin_pi(codigo_bin_pi),
        .catodo_po(catodo_po)
    );

    // Archivo de ondas
    initial begin
        $dumpfile("binario_7seg.vcd");
        $dumpvars(0, binario_7seg_tb);
    end

    // Pruebas
    initial begin

        // 0
        codigo_bin_pi = 4'd0;
        #10;
        if (catodo_po != 7'b1000000)
            $display("ERROR: entrada 0, salida = %b, esperada = 1000000", catodo_po);

        // 1
        codigo_bin_pi = 4'd1;
        #10;
        if (catodo_po != 7'b1111011)
            $display("ERROR: entrada 1, salida = %b, esperada = 1111011", catodo_po);

        // 2
        codigo_bin_pi = 4'd2;
        #10;
        if (catodo_po != 7'b0100100)
            $display("ERROR: entrada 2, salida = %b, esperada = 0100100", catodo_po);

        // 3
        codigo_bin_pi = 4'd3;
        #10;
        if (catodo_po != 7'b0110000)
            $display("ERROR: entrada 3, salida = %b, esperada = 0110000", catodo_po);

        // 4
        codigo_bin_pi = 4'd4;
        #10;
        if (catodo_po != 7'b0011001)
            $display("ERROR: entrada 4, salida = %b, esperada = 0011001", catodo_po);

        // 5
        codigo_bin_pi = 4'd5;
        #10;
        if (catodo_po != 7'b0010010)
            $display("ERROR: entrada 5, salida = %b, esperada = 0010010", catodo_po);

        // 6
        codigo_bin_pi = 4'd6;
        #10;
        if (catodo_po != 7'b0000010)
            $display("ERROR: entrada 6, salida = %b, esperada = 0000010", catodo_po);

        // 7
        codigo_bin_pi = 4'd7;
        #10;
        if (catodo_po != 7'b1111000)
            $display("ERROR: entrada 7, salida = %b, esperada = 1111000", catodo_po);

        // 8
        codigo_bin_pi = 4'd8;
        #10;
        if (catodo_po != 7'b0000000)
            $display("ERROR: entrada 8, salida = %b, esperada = 0000000", catodo_po);

        // 9
        codigo_bin_pi = 4'd9;
        #10;
        if (catodo_po != 7'b0010000)
            $display("ERROR: entrada 9, salida = %b, esperada = 0010000", catodo_po);

        // A
        codigo_bin_pi = 4'd10;
        #10;
        if (catodo_po != 7'b0001000)
            $display("ERROR: entrada A, salida = %b, esperada = 0001000", catodo_po);

        // B
        codigo_bin_pi = 4'd11;
        #10;
        if (catodo_po != 7'b0000011)
            $display("ERROR: entrada B, salida = %b, esperada = 0000011", catodo_po);

        // C
        codigo_bin_pi = 4'd12;
        #10;
        if (catodo_po != 7'b1000110)
            $display("ERROR: entrada C, salida = %b, esperada = 1000110", catodo_po);

        // D
        codigo_bin_pi = 4'd13;
        #10;
        if (catodo_po != 7'b0100001)
            $display("ERROR: entrada D, salida = %b, esperada = 0100001", catodo_po);

        // E
        codigo_bin_pi = 4'd14;
        #10;
        if (catodo_po != 7'b0000110)
            $display("ERROR: entrada E, salida = %b, esperada = 0000110", catodo_po);

        // F
        codigo_bin_pi = 4'd15;
        #10;
        if (catodo_po != 7'b0001110)
            $display("ERROR: entrada F, salida = %b, esperada = 0001110", catodo_po);

        $finish;

    end

endmodule

EL-3307_template/src/build/binario_7seg.vcd
$date
	Tue Sep 22 06:35:59 2026
$end
$version
	Icarus Verilog
$end
$timescale
	1ps
$end
$scope module binario_7seg_tb $end
$var wire 7 ! catodo_po [6:0] $end
$var reg 4 " codigo_bin_pi [3:0] $end
$scope module DUT $end
$var wire 1 # a $end
$var wire 1 $ b $end
$var wire 1 % c $end
$var wire 4 & codigo_bin_pi [3:0] $end
$var wire 1 ' d $end
$var wire 1 ( e $end
$var wire 1 ) f $end
$var wire 1 * g $end
$var wire 1 + i3 $end
$var wire 1 , i2 $end
$var wire 1 - i1 $end
$var wire 1 . i0 $end
$var wire 7 / catodo_po [6:0] $end
$upscope $end
$upscope $end
$enddefinitions $end
$comment Show the parameter values. $end
$dumpall
$end
#0
$dumpvars
b10000 /
0.
0-
0,
0+
1*
0)
0(
0'
b0 &
0%
0$
0#
b0 "
b10000 !
$end
#10000
1)
1'
1#
b111101 !
b111101 /
1(
1.
b1 "
b1 &
#20000
0*
0'
0#
1%
b1100000 !
b1100000 /
0(
1-
0.
b10 "
b10 &
#30000
0%
b100100 !
b100100 /
1(
1.
b11 "
b11 &
#40000
0)
1'
b1101 !
b1101 /
1#
1,
0-
0.
b100 "
b100 &
#50000
0'
0#
b110 !
b110 /
1$
1.
b101 "
b101 &
#60000
b10 !
b10 /
0(
1-
0.
b110 "
b110 &
#70000
1*
1)
1'
0$
b111100 !
b111100 /
1(
1.
b111 "
b111 &
#80000
0)
0*
0'
b0 !
b0 /
0(
1+
0,
0-
0.
b1000 "
b1000 &
#90000
b100 !
b100 /
1(
1.
b1001 "
b1001 &
#100000
1'
b1000 !
b1000 /
0(
1-
0.
b1010 "
b1010 &
#110000
0'
1#
b11 !
b11 /
1$
1.
b1011 "
b1011 &
#120000
0#
1%
b1010010 !
b1010010 /
1*
1,
0-
0.
b1100 "
b1100 &
#130000
1#
0*
1)
0%
b100001 !
b100001 /
0$
1.
b1101 "
b1101 &
#140000
0#
1%
1$
b1000010 !
b1000010 /
0)
1-
0.
b1110 "
b1110 &
#150000
b1001010 !
b1001010 /
1'
1.
b1111 "
b1111 &
