EL-3307_template/src/design/correccion_error.sv
module correccion_error (
    input  wire [6:0] palabra_rx, // Palabra recibida sin la paridad
    input  wire       paridad_mal, // Viene del módulo de verificador_paridad 
    input  wire [2:0] sindrome, // Viene del módulo de sindrome_hamming

    output wire [3:0] datos_corregidos, // La palabra corregida en i3 i2 i1 i0
    output wire       DED // Si hay doble error
);

    // Detecta si el síndrome es diferente de cero
    wire sindrome_error;

    assign sindrome_error = sindrome[2] | sindrome[1] | sindrome[0]; // Ve si alguno de los bits del síndrome es 1

    // Doble error: paridad correcta pero síndrome diferente de cero
    assign DED = ~paridad_mal & sindrome_error;


    // SEC: paridad mala y síndrome diferente de cero
    wire SEC;

    assign SEC = paridad_mal & sindrome_error;


    // Señales para invertir cada bit de Hamming (para corregir)
    wire error_1;
    wire error_2;
    wire error_3;
    wire error_4;
    wire error_5;
    wire error_6;
    wire error_7;

    assign error_1 = SEC & ~sindrome[2] & ~sindrome[1] &  sindrome[0];
    assign error_2 = SEC & ~sindrome[2] &  sindrome[1] & ~sindrome[0];
    assign error_3 = SEC & ~sindrome[2] &  sindrome[1] &  sindrome[0];
    assign error_4 = SEC &  sindrome[2] & ~sindrome[1] & ~sindrome[0];
    assign error_5 = SEC &  sindrome[2] & ~sindrome[1] &  sindrome[0];
    assign error_6 = SEC &  sindrome[2] &  sindrome[1] & ~sindrome[0];
    assign error_7 = SEC &  sindrome[2] &  sindrome[1] &  sindrome[0];


    // Corrección de los bits recibidos
    wire [6:0] palabra_corregida;

    assign palabra_corregida[0] = palabra_rx[0] ^ error_1;
    assign palabra_corregida[1] = palabra_rx[1] ^ error_2;
    assign palabra_corregida[2] = palabra_rx[2] ^ error_3;
    assign palabra_corregida[3] = palabra_rx[3] ^ error_4;
    assign palabra_corregida[4] = palabra_rx[4] ^ error_5;
    assign palabra_corregida[5] = palabra_rx[5] ^ error_6;
    assign palabra_corregida[6] = palabra_rx[6] ^ error_7;


    // Extraemos solamente los 4 bits de información
    assign datos_corregidos[3] = palabra_corregida[6]; // i3
    assign datos_corregidos[2] = palabra_corregida[5]; // i2
    assign datos_corregidos[1] = palabra_corregida[4]; // i1
    assign datos_corregidos[0] = palabra_corregida[2]; // i0

endmodule

EL-3307_template/src/sim/tb_correccion_error.sv
`timescale 1ns/1ps

module tb_correccion_error;

    // Entradas del DUT
    reg [6:0] palabra_rx;
    reg       paridad_mal;
    reg [2:0] sindrome;

    // Salidas del DUT
    wire [3:0] datos_corregidos;
    wire       DED;

    // Instancia del módulo a probar
    correccion_error DUT (
        .palabra_rx(palabra_rx),
        .paridad_mal(paridad_mal),
        .sindrome(sindrome),
        .datos_corregidos(datos_corregidos),
        .DED(DED)
    );

    initial begin
        $dumpfile("correccion_error.vcd");
        $dumpvars(0, tb_correccion_error);

        $display("==============================================");
        $display("       TESTBENCH - CORRECCION DE ERROR");
        $display("==============================================");

        // --------------------------------------------------
        // PRUEBA 1: SIN ERROR
        // --------------------------------------------------

        palabra_rx  = 7'b1010101;
        paridad_mal = 1'b0;
        sindrome    = 3'b000;

        #10;

        $display("");
        $display("Prueba 1 - Sin error");
        $display("Palabra RX     : %b", palabra_rx);
        $display("Paridad mal    : %b", paridad_mal);
        $display("Sindrome       : %b", sindrome);
        $display("Datos correg.  : %b", datos_corregidos);
        $display("DED            : %b", DED);


        // --------------------------------------------------
        // PRUEBA 2: ERROR EN POSICION 1
        // --------------------------------------------------

        palabra_rx  = 7'b1010100;
        paridad_mal = 1'b1;
        sindrome    = 3'b001;

        #10;

        $display("");
        $display("Prueba 2 - Error en posicion 1");
        $display("Palabra RX     : %b", palabra_rx);
        $display("Paridad mal    : %b", paridad_mal);
        $display("Sindrome       : %b", sindrome);
        $display("Datos correg.  : %b", datos_corregidos);
        $display("DED            : %b", DED);


        // --------------------------------------------------
        // PRUEBA 3: ERROR EN POSICION 2
        // --------------------------------------------------

        palabra_rx  = 7'b1010111;   
        paridad_mal = 1'b1;
        sindrome    = 3'b010;

        #10;

        $display("");
        $display("Prueba 3 - Error en posicion 2");
        $display("Palabra RX     : %b", palabra_rx);
        $display("Paridad mal    : %b", paridad_mal);
        $display("Sindrome       : %b", sindrome);
        $display("Datos correg.  : %b", datos_corregidos);
        $display("DED            : %b", DED);


        // --------------------------------------------------
        // PRUEBA 4: ERROR EN POSICION 3
        // --------------------------------------------------

        palabra_rx  = 7'b1010001;
        paridad_mal = 1'b1;
        sindrome    = 3'b011;

        #10;

        $display("");
        $display("Prueba 4 - Error en posicion 3");
        $display("Palabra RX     : %b", palabra_rx);
        $display("Paridad mal    : %b", paridad_mal);
        $display("Sindrome       : %b", sindrome);
        $display("Datos correg.  : %b", datos_corregidos);
        $display("DED            : %b", DED);


        // --------------------------------------------------
        // PRUEBA 5: ERROR EN POSICION 4
        // --------------------------------------------------

        palabra_rx  = 7'b1011101;
        paridad_mal = 1'b1;
        sindrome    = 3'b100;

        #10;

        $display("");
        $display("Prueba 5 - Error en posicion 4");
        $display("Palabra RX     : %b", palabra_rx);
        $display("Paridad mal    : %b", paridad_mal);
        $display("Sindrome       : %b", sindrome);
        $display("Datos correg.  : %b", datos_corregidos);
        $display("DED            : %b", DED);


        // --------------------------------------------------
        // PRUEBA 6: ERROR EN POSICION 5
        // --------------------------------------------------

        palabra_rx  = 7'b1000101;
        paridad_mal = 1'b1;
        sindrome    = 3'b101;

        #10;

        $display("");
        $display("Prueba 6 - Error en posicion 5");
        $display("Palabra RX     : %b", palabra_rx);
        $display("Paridad mal    : %b", paridad_mal);
        $display("Sindrome       : %b", sindrome);
        $display("Datos correg.  : %b", datos_corregidos);
        $display("DED            : %b", DED);


        // --------------------------------------------------
        // PRUEBA 7: ERROR EN POSICION 6
        // --------------------------------------------------

        palabra_rx  = 7'b1110101;
        paridad_mal = 1'b1;
        sindrome    = 3'b110;

        #10;

        $display("");
        $display("Prueba 7 - Error en posicion 6");
        $display("Palabra RX     : %b", palabra_rx);
        $display("Paridad mal    : %b", paridad_mal);
        $display("Sindrome       : %b", sindrome);
        $display("Datos correg.  : %b", datos_corregidos);
        $display("DED            : %b", DED);


        // --------------------------------------------------
        // PRUEBA 8: ERROR EN POSICION 7
        // --------------------------------------------------

        palabra_rx  = 7'b0010101;
        paridad_mal = 1'b1;
        sindrome    = 3'b111;

        #10;

        $display("");
        $display("Prueba 8 - Error en posicion 7");
        $display("Palabra RX     : %b", palabra_rx);
        $display("Paridad mal    : %b", paridad_mal);
        $display("Sindrome       : %b", sindrome);
        $display("Datos correg.  : %b", datos_corregidos);
        $display("DED            : %b", DED);


        // --------------------------------------------------
        // PRUEBA 9: DOBLE ERROR
        // --------------------------------------------------

        palabra_rx  = 7'b1100101;
        paridad_mal = 1'b0;
        sindrome    = 3'b011;

        #10;

        $display("");
        $display("Prueba 9 - Doble error");
        $display("Palabra RX     : %b", palabra_rx);
        $display("Paridad mal    : %b", paridad_mal);
        $display("Sindrome       : %b", sindrome);
        $display("Datos correg.  : %b", datos_corregidos);
        $display("DED            : %b", DED);


        // --------------------------------------------------
        // PRUEBA 10: ERROR SOLO EN PARIDAD GLOBAL
        // --------------------------------------------------

        palabra_rx  = 7'b1010101;
        paridad_mal = 1'b1;
        sindrome    = 3'b000;

        #10;

        $display("");
        $display("Prueba 10 - Error en paridad global");
        $display("Palabra RX     : %b", palabra_rx);
        $display("Paridad mal    : %b", paridad_mal);
        $display("Sindrome       : %b", sindrome);
        $display("Datos correg.  : %b", datos_corregidos);
        $display("DED            : %b", DED);


        $display("");
        $display("==============================================");
        $display("              FIN DE SIMULACION :DD");
        $display("==============================================");

        $finish;
    end

endmodule

EL-3307_template/src/build/correccion_error.vcd
$date
	Mon Sep 21 00:10:36 2026
$end
$version
	Icarus Verilog
$end
$timescale
	1ps
$end
$scope module tb_correccion_error $end
$var wire 4 ! datos_corregidos [3:0] $end
$var wire 1 " DED $end
$var reg 7 # palabra_rx [6:0] $end
$var reg 1 $ paridad_mal $end
$var reg 3 % sindrome [2:0] $end
$scope module DUT $end
$var wire 1 " DED $end
$var wire 1 & SEC $end
$var wire 1 ' error_1 $end
$var wire 1 ( error_2 $end
$var wire 1 ) error_3 $end
$var wire 1 * error_4 $end
$var wire 1 + error_5 $end
$var wire 1 , error_6 $end
$var wire 1 - error_7 $end
$var wire 7 . palabra_rx [6:0] $end
$var wire 1 $ paridad_mal $end
$var wire 3 / sindrome [2:0] $end
$var wire 1 0 sindrome_error $end
$var wire 7 1 palabra_corregida [6:0] $end
$var wire 4 2 datos_corregidos [3:0] $end
$upscope $end
$upscope $end
$enddefinitions $end
$comment Show the parameter values. $end
$dumpall
$end
#0
$dumpvars
b1011 2
b1010101 1
00
b0 /
b1010101 .
0-
0,
0+
0*
0)
0(
0'
0&
b0 %
0$
b1010101 #
0"
b1011 !
$end
#10000
1'
1&
10
b1010101 1
b1 %
b1 /
1$
b1010100 #
b1010100 .
#20000
1&
1(
10
0'
b1010101 1
b10 %
b10 /
b1010111 #
b1010111 .
#30000
0(
b1011 !
b1011 2
1)
b1010101 1
b11 %
b11 /
b1010001 #
b1010001 .
#40000
1*
b1011 !
b1011 2
0)
b1010101 1
b100 %
b100 /
b1011101 #
b1011101 .
#50000
0*
b1011 !
b1011 2
1+
b1010101 1
b101 %
b101 /
b1000101 #
b1000101 .
#60000
0*
1,
b1011 !
b1011 2
0+
b1010101 1
b110 %
b110 /
b1110101 #
b1110101 .
#70000
0,
b1011 !
b1011 2
1-
b1010101 1
b111 %
b111 /
b10101 #
b10101 .
#80000
0-
b1101 !
b1101 2
1"
b1100101 1
0&
b11 %
b11 /
0$
b1100101 #
b1100101 .
#90000
00
b1011 !
b1011 2
0"
b1010101 1
0&
b0 %
b0 /
1$
b1010101 #
b1010101 .
