EL-3307_template/src/design/sindrome_hamming.sv
module sindrome_hamming (
    // Me dice la posición de error
    input  wire [6:0] palabra_pi, // Recibe 7 bits, no incluida la paridad
    output wire [2:0] sindrome_po // Salen 3 bits: s0 s1 s2
);

    // S0 que revisa C0, i0, i1 e i3
    assign sindrome_po[0] = palabra_pi[0] ^ palabra_pi[2] ^
                            palabra_pi[4] ^ palabra_pi[6];

    // S1 que revisa C1, i0, i2 e i3
    assign sindrome_po[1] = palabra_pi[1] ^ palabra_pi[2] ^
                            palabra_pi[5] ^ palabra_pi[6];

    // S2 que revisa C2, i1, i2 e i3
    assign sindrome_po[2] = palabra_pi[3] ^ palabra_pi[4] ^
                            palabra_pi[5] ^ palabra_pi[6];
    // Llega hasta el bit 7, no revisa la paridad

endmodule

EL-3307_template/src/sim/tb_sindrome_hamming.sv
`timescale 1ns/1ps

module tb_sindrome_hamming;

    // Entrada del DUT
    reg [6:0] palabra_pi;

    // Salida del DUT
    wire [2:0] sindrome_po;

    // Instancia del módulo a probar
    sindrome_hamming DUT (
        .palabra_pi(palabra_pi),
        .sindrome_po(sindrome_po)
    );

    initial begin
        $dumpfile("sindrome_hamming.vcd");
        $dumpvars(0, tb_sindrome_hamming);

        $display("==============================================");
        $display("      TESTBENCH - SINDROME HAMMING (7,4)");
        $display("==============================================");

        // ------------------------------------------
        // Prueba 1: Sin error
        // ------------------------------------------
        palabra_pi = 7'b0000000;
        #10;

        $display("Prueba 1 - Sin error");
        $display("Entrada  : %b", palabra_pi);
        $display("Sindrome : %b", sindrome_po);
        $display("----------------------------------------------");


        // ------------------------------------------
        // Prueba 2: Error en bit 1
        // ------------------------------------------
        palabra_pi = 7'b0000001;
        #10;

        $display("Prueba 2 - Error en bit 1");
        $display("Entrada  : %b", palabra_pi);
        $display("Sindrome : %b", sindrome_po);
        $display("----------------------------------------------");


        // ------------------------------------------
        // Prueba 3: Error en bit 2
        // ------------------------------------------
        palabra_pi = 7'b0000010;
        #10;

        $display("Prueba 3 - Error en bit 2");
        $display("Entrada  : %b", palabra_pi);
        $display("Sindrome : %b", sindrome_po);
        $display("----------------------------------------------");


        // ------------------------------------------
        // Prueba 4: Error en bit 3
        // ------------------------------------------
        palabra_pi = 7'b0000100;
        #10;

        $display("Prueba 4 - Error en bit 3");
        $display("Entrada  : %b", palabra_pi);
        $display("Sindrome : %b", sindrome_po);
        $display("----------------------------------------------");


        // ------------------------------------------
        // Prueba 5: Error en bit 4
        // ------------------------------------------
        palabra_pi = 7'b0001000;
        #10;

        $display("Prueba 5 - Error en bit 4");
        $display("Entrada  : %b", palabra_pi);
        $display("Sindrome : %b", sindrome_po);
        $display("----------------------------------------------");


        // ------------------------------------------
        // Prueba 6: Error en bit 5
        // ------------------------------------------
        palabra_pi = 7'b0010000;
        #10;

        $display("Prueba 6 - Error en bit 5");
        $display("Entrada  : %b", palabra_pi);
        $display("Sindrome : %b", sindrome_po);
        $display("----------------------------------------------");


        // ------------------------------------------
        // Prueba 7: Error en bit 6
        // ------------------------------------------
        palabra_pi = 7'b0100000;
        #10;

        $display("Prueba 7 - Error en bit 6");
        $display("Entrada  : %b", palabra_pi);
        $display("Sindrome : %b", sindrome_po);
        $display("----------------------------------------------");


        // ------------------------------------------
        // Prueba 8: Error en bit 7
        // ------------------------------------------
        palabra_pi = 7'b1000000;
        #10;

        $display("Prueba 8 - Error en bit 7");
        $display("Entrada  : %b", palabra_pi);
        $display("Sindrome : %b", sindrome_po);
        $display("----------------------------------------------");


        // ------------------------------------------
        // Prueba 9: Varios bits en 1
        // ------------------------------------------
        palabra_pi = 7'b1010101;
        #10;

        $display("Prueba 9 - Caso general");
        $display("Entrada  : %b", palabra_pi);
        $display("Sindrome : %b", sindrome_po);
        $display("----------------------------------------------");


        $display("==============================================");
        $display("             FIN DE SIMULACION :DDD");
        $display("==============================================");

        $finish;
    end

endmodule

EL-3307_template/src/build/sindrome_hamming.vcd
$date
	Sun Sep 20 23:47:39 2026
$end
$version
	Icarus Verilog
$end
$timescale
	1ps
$end
$scope module tb_sindrome_hamming $end
$var wire 3 ! sindrome_po [2:0] $end
$var reg 7 " palabra_pi [6:0] $end
$scope module DUT $end
$var wire 7 # palabra_pi [6:0] $end
$var wire 3 $ sindrome_po [2:0] $end
$upscope $end
$upscope $end
$enddefinitions $end
$comment Show the parameter values. $end
$dumpall
$end
#0
$dumpvars
b0 $
b0 #
b0 "
b0 !
$end
#10000
b1 !
b1 $
b1 "
b1 #
#20000
b10 !
b10 $
b10 "
b10 #
#30000
b11 !
b11 $
b100 "
b100 #
#40000
b100 !
b100 $
b1000 "
b1000 #
#50000
b101 !
b101 $
b10000 "
b10000 #
#60000
b110 !
b110 $
b100000 "
b100000 #
#70000
b111 !
b111 $
b1000000 "
b1000000 #
#80000
b0 !
b0 $
b1010101 "
b1010101 #
