EL-3307_template/src/design/despliegue_receptor.sv
module despliegue_receptor (

    input  wire [3:0] palabra_pi,        // Palabra recibida
    input  wire [2:0] sindrome_pi,       // Síndrome / posición del error
    input  wire       doble_error_pi,    // 1 = doble error (DED)
    input  wire       display_pi,        // 0 = palabra, 1 = síndrome

    output wire [3:0] codigo_bin_led_po, // LEDs de la palabra
    output wire [6:0] catodo_po,         // Segmentos
    output wire [1:0] anodo_po           // Selección de display

);

    // ========================================================
    // DATO A MOSTRAR
    //
    // display_pi = 0 -> palabra recibida
    // display_pi = 1 -> síndrome
    //
    // Si hay doble error -> 1110 = E
    // ========================================================

    wire [3:0] dato_mostrar;


    // --------------------------------------------------------
    // Bit 0
    // --------------------------------------------------------

    assign dato_mostrar[0] =
        ~doble_error_pi &
        (
            (~display_pi & palabra_pi[0]) |
            ( display_pi & sindrome_pi[0])
        );


    // --------------------------------------------------------
    // Bit 1
    // --------------------------------------------------------

    assign dato_mostrar[1] =
        doble_error_pi |
        (
            ~doble_error_pi &
            (
                (~display_pi & palabra_pi[1]) |
                ( display_pi & sindrome_pi[1])
            )
        );


    // --------------------------------------------------------
    // Bit 2
    // --------------------------------------------------------

    assign dato_mostrar[2] =
        doble_error_pi |
        (
            ~doble_error_pi &
            (
                (~display_pi & palabra_pi[2]) |
                ( display_pi & sindrome_pi[2])
            )
        );


    // --------------------------------------------------------
    // Bit 3
    //
    // En DED se pone en 1.
    // Resultado final en DED:
    //
    // dato_mostrar = 1110 = E
    // --------------------------------------------------------

    assign dato_mostrar[3] =
        doble_error_pi |
        (
            ~doble_error_pi &
            ~display_pi &
            palabra_pi[3]
        );


    // ========================================================
    // LEDs
    //
    // Los LEDs muestran siempre la palabra recibida.
    // El switch display NO afecta estos LEDs.
    // ========================================================

    assign codigo_bin_led_po = palabra_pi;


    // ========================================================
    // DECODIFICADOR HEXADECIMAL A 7 SEGMENTOS
    //
    // Las ecuaciones generan segmentos:
    //
    // a,b,c,d,e,f,g
    //
    // activos en alto.
    // ========================================================

    wire a;
    wire b;
    wire c;
    wire d;
    wire e;
    wire f;
    wire g;


    // --------------------------------------------------------
    // Segmento A
    // --------------------------------------------------------

    assign a =
          (dato_mostrar[1] & dato_mostrar[2]) |
          (dato_mostrar[1] & ~dato_mostrar[3]) |
          (dato_mostrar[3] & ~dato_mostrar[0]) |
          (~dato_mostrar[0] & ~dato_mostrar[2]) |
          (dato_mostrar[0] & dato_mostrar[2] & ~dato_mostrar[3]) |
          (dato_mostrar[3] & ~dato_mostrar[1] & ~dato_mostrar[2]);


    // --------------------------------------------------------
    // Segmento B
    // --------------------------------------------------------

    assign b =
          (~dato_mostrar[0] & ~dato_mostrar[2]) |
          (~dato_mostrar[2] & ~dato_mostrar[3]) |
          (dato_mostrar[0] & dato_mostrar[1] & ~dato_mostrar[3]) |
          (dato_mostrar[0] & dato_mostrar[3] & ~dato_mostrar[1]) |
          (~dato_mostrar[0] & ~dato_mostrar[1] & ~dato_mostrar[3]);


    // --------------------------------------------------------
    // Segmento C
    // --------------------------------------------------------

    assign c =
          (dato_mostrar[0] & ~dato_mostrar[1]) |
          (dato_mostrar[0] & ~dato_mostrar[3]) |
          (dato_mostrar[2] & ~dato_mostrar[3]) |
          (dato_mostrar[3] & ~dato_mostrar[2]) |
          (~dato_mostrar[1] & ~dato_mostrar[3]);


    // --------------------------------------------------------
    // Segmento D
    // --------------------------------------------------------

    assign d =
          (dato_mostrar[3] & ~dato_mostrar[1]) |
          (dato_mostrar[0] & dato_mostrar[1] & ~dato_mostrar[2]) |
          (dato_mostrar[0] & dato_mostrar[2] & ~dato_mostrar[1]) |
          (dato_mostrar[1] & dato_mostrar[2] & ~dato_mostrar[0]) |
          (~dato_mostrar[0] & ~dato_mostrar[2] & ~dato_mostrar[3]);


    // --------------------------------------------------------
    // Segmento E
    // --------------------------------------------------------

    assign e =
          (dato_mostrar[1] & dato_mostrar[3]) |
          (dato_mostrar[2] & dato_mostrar[3]) |
          (dato_mostrar[1] & ~dato_mostrar[0]) |
          (~dato_mostrar[0] & ~dato_mostrar[2]);


    // --------------------------------------------------------
    // Segmento F
    // --------------------------------------------------------

    assign f =
          (dato_mostrar[1] & dato_mostrar[3]) |
          (dato_mostrar[2] & ~dato_mostrar[0]) |
          (dato_mostrar[3] & ~dato_mostrar[2]) |
          (~dato_mostrar[0] & ~dato_mostrar[1]) |
          (dato_mostrar[2] & ~dato_mostrar[1] & ~dato_mostrar[3]);


    // --------------------------------------------------------
    // Segmento G
    // --------------------------------------------------------

    assign g =
          (dato_mostrar[0] & dato_mostrar[3]) |
          (dato_mostrar[1] & ~dato_mostrar[0]) |
          (dato_mostrar[1] & ~dato_mostrar[2]) |
          (dato_mostrar[3] & ~dato_mostrar[2]) |
          (dato_mostrar[2] & ~dato_mostrar[1] & ~dato_mostrar[3]);


    // ========================================================
    // MAPEO DE SEGMENTOS
    //
    // CABLEADO FÍSICO ACTUAL:
    //
    // FPGA 76 -> A
    // FPGA 75 -> B
    // FPGA 72 -> E
    // FPGA 71 -> D
    // FPGA 70 -> G
    // FPGA 74 -> F
    // FPGA 73 -> C
    //
    // Display de ánodo común:
    // 0 = encendido
    // 1 = apagado
    // ========================================================

    assign catodo_po[0] = ~a;    // Pin 76 -> A
    assign catodo_po[1] = ~b;    // Pin 75 -> B
    assign catodo_po[2] = ~e;    // Pin 72 -> E
    assign catodo_po[3] = ~d;    // Pin 71 -> D
    assign catodo_po[4] = ~g;    // Pin 70 -> G
    assign catodo_po[5] = ~f;    // Pin 74 -> F
    assign catodo_po[6] = ~c;    // Pin 73 -> C


    // ========================================================
    // SELECCIÓN DEL DISPLAY
    //
    // PNP:
    // 0 = display encendido
    // 1 = display apagado
    //
    // display_pi = 0 -> display 0
    // display_pi = 1 -> display 1
    // ========================================================

    assign anodo_po[0] = display_pi;
    assign anodo_po[1] = ~display_pi;


endmodule

EL-3307_template/src/sim/tb_despliegue_receptor.sv
`timescale 1ns/1ps

module tb_despliegue_receptor;

    // ========================================================
    // ENTRADAS DEL DUT
    // ========================================================

    reg [3:0] palabra_pi;
    reg [2:0] sindrome_pi;
    reg       doble_error_pi;
    reg       display_pi;

    // ========================================================
    // SALIDAS DEL DUT
    // ========================================================

    wire [3:0] codigo_bin_led_po;
    wire [6:0] catodo_po;
    wire [1:0] anodo_po;

    // ========================================================
    // INSTANCIA DEL MODULO
    // ========================================================

    despliegue_receptor DUT (

        .palabra_pi(palabra_pi),
        .sindrome_pi(sindrome_pi),
        .doble_error_pi(doble_error_pi),
        .display_pi(display_pi),

        .codigo_bin_led_po(codigo_bin_led_po),
        .catodo_po(catodo_po),
        .anodo_po(anodo_po)

    );

    // ========================================================
    // ARCHIVO DE ONDAS
    // ========================================================

    initial begin
        $dumpfile("tb_despliegue_receptor.vcd");
        $dumpvars(0, tb_despliegue_receptor);
    end


    // ========================================================
    // PRUEBAS
    // ========================================================

    initial begin

        $display("==============================================");
        $display(" TESTBENCH - DESPLIEGUE RECEPTOR");
        $display("==============================================");


        // ----------------------------------------------------
        // INICIALIZACION
        // ----------------------------------------------------

        palabra_pi     = 4'b0000;
        sindrome_pi    = 3'b000;
        doble_error_pi = 1'b0;
        display_pi     = 1'b0;

        #10;


        // ====================================================
        // PRUEBA 1
        // Mostrar palabra 0
        // ====================================================

        palabra_pi     = 4'b0000;
        sindrome_pi    = 3'b000;
        doble_error_pi = 1'b0;
        display_pi     = 1'b0;

        #10;

        $display("");
        $display("Prueba 1 - Mostrar palabra 0");
        $display("Palabra       : %b", palabra_pi);
        $display("Sindrome      : %b", sindrome_pi);
        $display("DED           : %b", doble_error_pi);
        $display("Display       : %b", display_pi);
        $display("LEDs          : %b", codigo_bin_led_po);
        $display("Catodos       : %b", catodo_po);
        $display("Anodos        : %b", anodo_po);


        // ====================================================
        // PRUEBA 2
        // Mostrar palabra 5
        // ====================================================

        palabra_pi     = 4'b0101;
        sindrome_pi    = 3'b000;
        doble_error_pi = 1'b0;
        display_pi     = 1'b0;

        #10;

        $display("");
        $display("Prueba 2 - Mostrar palabra 5");
        $display("Palabra       : %b", palabra_pi);
        $display("Sindrome      : %b", sindrome_pi);
        $display("DED           : %b", doble_error_pi);
        $display("Display       : %b", display_pi);
        $display("LEDs          : %b", codigo_bin_led_po);
        $display("Catodos       : %b", catodo_po);
        $display("Anodos        : %b", anodo_po);


        // ====================================================
        // PRUEBA 3
        // Mostrar palabra A
        // ====================================================

        palabra_pi     = 4'b1010;
        sindrome_pi    = 3'b000;
        doble_error_pi = 1'b0;
        display_pi     = 1'b0;

        #10;

        $display("");
        $display("Prueba 3 - Mostrar palabra A");
        $display("Palabra       : %b", palabra_pi);
        $display("Sindrome      : %b", sindrome_pi);
        $display("DED           : %b", doble_error_pi);
        $display("Display       : %b", display_pi);
        $display("LEDs          : %b", codigo_bin_led_po);
        $display("Catodos       : %b", catodo_po);
        $display("Anodos        : %b", anodo_po);


        // ====================================================
        // PRUEBA 4
        // Mostrar palabra F
        // ====================================================

        palabra_pi     = 4'b1111;
        sindrome_pi    = 3'b000;
        doble_error_pi = 1'b0;
        display_pi     = 1'b0;

        #10;

        $display("");
        $display("Prueba 4 - Mostrar palabra F");
        $display("Palabra       : %b", palabra_pi);
        $display("Sindrome      : %b", sindrome_pi);
        $display("DED           : %b", doble_error_pi);
        $display("Display       : %b", display_pi);
        $display("LEDs          : %b", codigo_bin_led_po);
        $display("Catodos       : %b", catodo_po);
        $display("Anodos        : %b", anodo_po);


        // ====================================================
        // PRUEBA 5
        // Mostrar sindrome 001
        // ====================================================

        palabra_pi     = 4'b1010;
        sindrome_pi    = 3'b001;
        doble_error_pi = 1'b0;
        display_pi     = 1'b1;

        #10;

        $display("");
        $display("Prueba 5 - Mostrar sindrome 1");
        $display("Palabra       : %b", palabra_pi);
        $display("Sindrome      : %b", sindrome_pi);
        $display("DED           : %b", doble_error_pi);
        $display("Display       : %b", display_pi);
        $display("LEDs          : %b", codigo_bin_led_po);
        $display("Catodos       : %b", catodo_po);
        $display("Anodos        : %b", anodo_po);


        // ====================================================
        // PRUEBA 6
        // Mostrar sindrome 011
        // ====================================================

        palabra_pi     = 4'b0101;
        sindrome_pi    = 3'b011;
        doble_error_pi = 1'b0;
        display_pi     = 1'b1;

        #10;

        $display("");
        $display("Prueba 6 - Mostrar sindrome 3");
        $display("Palabra       : %b", palabra_pi);
        $display("Sindrome      : %b", sindrome_pi);
        $display("DED           : %b", doble_error_pi);
        $display("Display       : %b", display_pi);
        $display("LEDs          : %b", codigo_bin_led_po);
        $display("Catodos       : %b", catodo_po);
        $display("Anodos        : %b", anodo_po);


        // ====================================================
        // PRUEBA 7
        // Mostrar sindrome 111
        // ====================================================

        palabra_pi     = 4'b0011;
        sindrome_pi    = 3'b111;
        doble_error_pi = 1'b0;
        display_pi     = 1'b1;

        #10;

        $display("");
        $display("Prueba 7 - Mostrar sindrome 7");
        $display("Palabra       : %b", palabra_pi);
        $display("Sindrome      : %b", sindrome_pi);
        $display("DED           : %b", doble_error_pi);
        $display("Display       : %b", display_pi);
        $display("LEDs          : %b", codigo_bin_led_po);
        $display("Catodos       : %b", catodo_po);
        $display("Anodos        : %b", anodo_po);


        // ====================================================
        // PRUEBA 8
        // DOBLE ERROR
        // ====================================================

        palabra_pi     = 4'b1010;
        sindrome_pi    = 3'b011;
        doble_error_pi = 1'b1;
        display_pi     = 1'b0;

        #10;

        $display("");
        $display("Prueba 8 - DOBLE ERROR");
        $display("Palabra       : %b", palabra_pi);
        $display("Sindrome      : %b", sindrome_pi);
        $display("DED           : %b", doble_error_pi);
        $display("Display       : %b", display_pi);
        $display("LEDs          : %b", codigo_bin_led_po);
        $display("Catodos       : %b", catodo_po);
        $display("Anodos        : %b", anodo_po);


        // ====================================================
        // PRUEBA 9
        // Verificar que los LEDs NO dependan de display_pi
        // ====================================================

        palabra_pi     = 4'b1100;
        sindrome_pi    = 3'b010;
        doble_error_pi = 1'b0;
        display_pi     = 1'b0;

        #10;

        $display("");
        $display("Prueba 9 - LEDs con display = 0");
        $display("Palabra       : %b", palabra_pi);
        $display("LEDs          : %b", codigo_bin_led_po);

        display_pi = 1'b1;

        #10;

        $display("");
        $display("Prueba 9 - LEDs con display = 1");
        $display("Palabra       : %b", palabra_pi);
        $display("LEDs          : %b", codigo_bin_led_po);


        // ====================================================
        // FINAL
        // ====================================================

        $display("");
        $display("==============================================");
        $display(" FIN DEL TESTBENCH :DD");
        $display("==============================================");

        #10;

        $finish;

    end

endmodule

EL-3307_template/src/build/tb_despliegue_receptor.vcd
$date
	Mon Sep 21 00:29:47 2026
$end
$version
	Icarus Verilog
$end
$timescale
	1ps
$end
$scope module tb_despliegue_receptor $end
$var wire 4 ! codigo_bin_led_po [3:0] $end
$var wire 7 " catodo_po [6:0] $end
$var wire 2 # anodo_po [1:0] $end
$var reg 1 $ display_pi $end
$var reg 1 % doble_error_pi $end
$var reg 4 & palabra_pi [3:0] $end
$var reg 3 ' sindrome_pi [2:0] $end
$scope module DUT $end
$var wire 1 ( a $end
$var wire 1 ) b $end
$var wire 1 * c $end
$var wire 4 + codigo_bin_led_po [3:0] $end
$var wire 1 , d $end
$var wire 1 $ display_pi $end
$var wire 1 % doble_error_pi $end
$var wire 1 - e $end
$var wire 1 . f $end
$var wire 1 / g $end
$var wire 4 0 palabra_pi [3:0] $end
$var wire 3 1 sindrome_pi [2:0] $end
$var wire 4 2 dato_mostrar [3:0] $end
$var wire 7 3 catodo_po [6:0] $end
$var wire 2 4 anodo_po [1:0] $end
$upscope $end
$upscope $end
$enddefinitions $end
$comment Show the parameter values. $end
$dumpall
$end
#0
$dumpvars
b10 4
b10000 3
b0 2
b0 1
b0 0
0/
1.
1-
1,
b0 +
1*
1)
1(
b0 '
b0 &
0%
0$
b10 #
b10000 "
b0 !
$end
#20000
0)
1,
b110 "
b110 3
1/
0-
b101 2
b101 !
b101 +
b101 &
b101 0
#30000
0,
1(
1)
1-
b1000 "
b1000 3
1.
1/
b1010 2
b1010 !
b1010 +
b1010 &
b1010 0
#40000
0)
b1001010 "
b1001010 3
0*
b1111 2
b1111 !
b1111 +
b1111 &
b1111 0
#50000
0(
1)
b111101 "
b111101 3
0.
0/
1*
0-
b1 2
b1 #
b1 4
1$
b1 '
b1 1
b1010 !
b1010 +
b1010 &
b1010 0
#60000
1(
1,
b100100 "
b100100 3
1/
b11 2
b11 '
b11 1
b101 !
b101 +
b101 &
b101 0
#70000
0,
b111100 "
b111100 3
0/
b111 2
b111 '
b111 1
b11 !
b11 +
b11 &
b11 0
#80000
0*
1,
0)
b1000010 "
b1000010 3
1.
1/
1-
b1110 2
b10 #
b10 4
0$
1%
b11 '
b11 1
b1010 !
b1010 +
b1010 &
b1010 0
#90000
0/
1,
0)
b1010010 "
b1010010 3
0*
b1100 2
0%
b10 '
b10 1
b1100 !
b1100 +
b1100 &
b1100 0
#100000
0.
1(
b1100000 "
b1100000 3
1)
1/
b10 2
b1 #
b1 4
1$
